{
  "type": "Collection",
  "id": "DE25",
  "stac_version": "1.1.0",
  "description": "Sindelfingen - DE",
  "links": [
    {
      "rel": "root",
      "href": "../../../catalog.json",
      "type": "application/json",
      "title": "RACE"
    },
    {
      "rel": "parent",
      "href": "../collection.json",
      "type": "application/json",
      "title": "Automobile inventory level"
    }
  ],
  "subcode": "DE25",
  "title": "Sindelfingen",
  "extent": {
    "spatial": {
      "bbox": [
        [
          null,
          null,
          null,
          null
        ]
      ]
    },
    "temporal": {
      "interval": [
        [
          null,
          null
        ]
      ]
    }
  },
  "license": "other"
}