{
  "type": "Collection",
  "id": "100026",
  "stac_version": "1.1.0",
  "description": "Schwechat - AT",
  "links": [
    {
      "rel": "root",
      "href": "../../../catalog.json",
      "type": "application/json",
      "title": "RACE"
    },
    {
      "rel": "parent",
      "href": "../collection.json",
      "type": "application/json",
      "title": "Crude Oil Storage Index"
    }
  ],
  "subcode": "100026",
  "title": "Schwechat",
  "extent": {
    "spatial": {
      "bbox": [
        [
          16.494681,
          48.134818,
          16.514681000000003,
          48.154818
        ]
      ]
    },
    "temporal": {
      "interval": [
        [
          "2017-01-09T00:00:00Z",
          "2024-01-01T00:00:00Z"
        ]
      ]
    }
  },
  "license": "other"
}