{
  "type": "Catalog",
  "id": "RACE",
  "stac_version": "1.1.0",
  "description": "Rapid Action for Citizens with Earth Observation",
  "links": [
    {
      "rel": "root",
      "href": "./catalog.json",
      "type": "application/json",
      "title": "RACE"
    },
    {
      "rel": "child",
      "href": "./ports_cars_aq/collection.json",
      "type": "application/json",
      "title": "Sources of pollution and NO2 levels",
      "subtitle": "Port Activities, sources of pollution and NO2 levels",
      "code": "C3",
      "id": "ports_cars_aq",
      "themes": [
        "economy",
        "air"
      ],
      "subcode": "C3",
      "satellite": [
        "Sentinel-5P",
        "GNSS"
      ],
      "sensor": [
        "TROPOMI"
      ],
      "cities": [
        "Gioia Tauro",
        "Genoa"
      ],
      "countries": [
        "IT"
      ],
      "thumbnail": [
        "https://raw.githubusercontent.com/eurodatacube/eodash-assets/main/collections/C3_ports_cars_aq/C3_ports_cars_aq_photo.jpg"
      ],
      "tags": [
        "Air quality",
        "NO2",
        "Ports",
        "Multi-sensors"
      ],
      "agency": [
        "ESA"
      ],
      "insituSources": [
        "AIS",
        "Mobile"
      ]
    },
    {
      "rel": "child",
      "href": "./CV_Covid_19_cases/collection.json",
      "type": "application/json",
      "title": "Covid-19 Cases",
      "code": "CV",
      "id": "CV_Covid_19_cases",
      "themes": [
        "health"
      ],
      "subcode": "CV",
      "cities": [
        "/"
      ],
      "countries": [
        "Spain",
        "Italy",
        "Serbia",
        "Sweden",
        "Bulgaria",
        "Albania",
        "Austria",
        "Estonia",
        "Switzerland",
        "Germany",
        "Czechia",
        "Ireland",
        "Latvia",
        "Lithuania",
        "Finland",
        "Slovakia",
        "Luxembourg",
        "Bosnia and Herzegovina",
        "United Kingdom",
        "Hungary",
        "Norway",
        "Turkey",
        "Croatia",
        "France",
        "Kosovo",
        "Netherlands",
        "Portugal",
        "Malta",
        "Belgium",
        "North Macedonia",
        "Poland",
        "Romania",
        "Denmark",
        "Slovenia",
        "Greece"
      ],
      "thumbnail": [
        "https://raw.githubusercontent.com/eurodatacube/eodash-assets/main/collections/CV_Covid_19_cases/CV_Covid_19_cases_photo.jpg"
      ],
      "tags": [
        "Covid-19",
        "Human activities",
        "Open data"
      ],
      "agency": [
        "ESA"
      ],
      "insituSources": [
        "Other"
      ]
    },
    {
      "rel": "child",
      "href": "./agricultural_production_productive_area/collection.json",
      "type": "application/json",
      "title": "Agricultural production - productive area",
      "subtitle": "Agricultural production in Europe",
      "code": "E10a1",
      "id": "agricultural_production_productive_area",
      "themes": [
        "agriculture"
      ],
      "subcode": "E10a1",
      "satellite": [
        "Sentinel-2"
      ],
      "sensor": [
        "MSI"
      ],
      "cities": [
        "Huelva (Lagunas de las Madres)",
        "Brandenburg"
      ],
      "countries": [
        "ES",
        "DE"
      ],
      "thumbnail": [
        "https://raw.githubusercontent.com/eurodatacube/eodash-assets/main/collections/E10a1_agricultural_production_productive_area/E10a1_agricultural_production_productive_area_photo.jpg"
      ],
      "tags": [
        "Copernicus",
        "Open data"
      ],
      "agency": [
        "ESA"
      ]
    },
    {
      "rel": "child",
      "href": "./agricultural_production_area/collection.json",
      "type": "application/json",
      "title": "Agricultural production - area",
      "subtitle": "Agricultural production in Europe",
      "code": "E10a2",
      "id": "agricultural_production_area",
      "themes": [
        "agriculture"
      ],
      "subcode": "E10a2",
      "satellite": [
        "Sentinel-2"
      ],
      "sensor": [
        "MSI"
      ],
      "cities": [
        "Brandenburg Region"
      ],
      "countries": [
        "DE"
      ],
      "thumbnail": [
        "https://raw.githubusercontent.com/eurodatacube/eodash-assets/main/collections/E10a2_agricultural_production_area/E10a2_agricultural_production_area_photo.jpg"
      ],
      "tags": [
        "Copernicus",
        "Open data"
      ],
      "agency": [
        "ESA"
      ]
    },
    {
      "rel": "child",
      "href": "./agricultural_production_area_change/collection.json",
      "type": "application/json",
      "title": "Agricultural production - area change",
      "subtitle": "Agricultural production in Europe",
      "code": "E10a3",
      "id": "agricultural_production_area_change",
      "themes": [
        "agriculture"
      ],
      "subcode": "E10a3",
      "satellite": [
        "Sentinel-2"
      ],
      "sensor": [
        "MSI"
      ],
      "cities": [
        "Brandenburg"
      ],
      "countries": [
        "DE"
      ],
      "thumbnail": [
        "https://raw.githubusercontent.com/eurodatacube/eodash-assets/main/collections/E10a3_agricultural_production_area_change/E10a3_agricultural_production_area_change_photo.jpg"
      ],
      "tags": [
        "Copernicus",
        "Open data"
      ],
      "agency": [
        "ESA"
      ]
    },
    {
      "rel": "child",
      "href": "./fruit_production/collection.json",
      "type": "application/json",
      "title": "Fruit production",
      "subtitle": "Monitoring fruit production (Berries) in Huelva, Spain",
      "code": "E10a5",
      "id": "fruit_production",
      "themes": [
        "agriculture"
      ],
      "subcode": "E10a5",
      "satellite": [
        "Sentinel-2",
        "Pleiades"
      ],
      "sensor": [
        "MSI",
        "HiRI"
      ],
      "cities": [
        "Huelva Laguna de las Madres"
      ],
      "countries": [
        "ES"
      ],
      "thumbnail": [
        "https://raw.githubusercontent.com/eurodatacube/eodash-assets/main/collections/E10a5_fruit_production/E10a5_fruit_production.jpg"
      ],
      "tags": [
        "Copernicus",
        "Multi-sensors"
      ],
      "agency": [
        "ESA",
        "CNES"
      ]
    },
    {
      "rel": "child",
      "href": "./agricultural_workers/collection.json",
      "type": "application/json",
      "title": "Agricultural workers",
      "subtitle": "Availability of agricultural workers",
      "code": "E10a9",
      "id": "agricultural_workers",
      "themes": [
        "agriculture"
      ],
      "subcode": "E10a9",
      "satellite": [
        "Sentinel-2",
        "Deimos-2"
      ],
      "sensor": [
        "MSI",
        "DMAC"
      ],
      "cities": [
        "Apulia"
      ],
      "countries": [
        "IT"
      ],
      "thumbnail": [
        "https://raw.githubusercontent.com/eurodatacube/eodash-assets/main/collections/E10a9_agricultural_workers/E10a9_agricultural_workers_photo.jpg"
      ],
      "tags": [
        "Land cover",
        "Multi-sensors"
      ],
      "agency": [
        "ESA"
      ],
      "insituSources": [
        "Mobile"
      ]
    },
    {
      "rel": "child",
      "href": "./shopping_center_activity/collection.json",
      "type": "application/json",
      "title": "Activity at shopping centers",
      "subtitle": "Occupancy of customer parking",
      "code": "E11",
      "id": "shopping_center_activity",
      "themes": [
        "economy"
      ],
      "subcode": "E11",
      "satellite": [
        "Sentinel-1"
      ],
      "sensor": [
        "C-SAR"
      ],
      "cities": [
        "Milan",
        "Athens",
        "Rome",
        "Bucharest",
        "Brussels",
        "Warsaw"
      ],
      "countries": [
        "RO",
        "PL",
        "GR",
        "IT",
        "BE"
      ],
      "thumbnail": [
        "https://raw.githubusercontent.com/eurodatacube/eodash-assets/main/collections/E11_shopping_center_activity/E11_shopping_center_activity_photo.jpg"
      ],
      "tags": [
        "Copernicus",
        "Mobility",
        "Traffic",
        "Open data"
      ],
      "agency": [
        "ESA"
      ],
      "insituSources": [
        "Mobile"
      ]
    },
    {
      "rel": "child",
      "href": "./border_crossing_vehicles_timeseries/collection.json",
      "type": "application/json",
      "title": "Border crossing vehicles time series",
      "subtitle": "Volume of highway occupancy from Sentinel-1 data",
      "code": "E12b",
      "id": "border_crossing_vehicles_timeseries",
      "themes": [
        "economy"
      ],
      "subcode": "E12b",
      "satellite": [
        "Sentinel-1"
      ],
      "sensor": [
        "C-SAR"
      ],
      "cities": [
        "Folkestone"
      ],
      "countries": [
        "GB"
      ],
      "thumbnail": [
        "https://raw.githubusercontent.com/eurodatacube/eodash-assets/main/collections/E12b_border_crossing_vehicles_timeseries/E12b_border_crossing_vehicles_timeseries_photo.jpg"
      ],
      "tags": [
        "Copernicus",
        "SAR",
        "Mobility",
        "Traffic",
        "Open data"
      ],
      "agency": [
        "ESA"
      ]
    },
    {
      "rel": "child",
      "href": "./flying_planes/collection.json",
      "type": "application/json",
      "title": "Flying planes detections",
      "subtitle": "Flying planes detected on Sentinel-2 data",
      "code": "E13d",
      "id": "flying_planes",
      "themes": [
        "economy"
      ],
      "subcode": "E13d",
      "satellite": [
        "Sentinel-2"
      ],
      "sensor": [
        "MSI"
      ],
      "cities": [
        "London",
        "Barcelona",
        "Helsinki",
        "Rome",
        "Zurich",
        "Brussels",
        "Paris",
        "Lisbon",
        "Palma de Mallorca",
        "Warsaw",
        "Oslo",
        "Milan",
        "Copenhagen",
        "Amsterdam",
        "Istanbul",
        "Frankfurt",
        "Malaga",
        "Vienna",
        "Munich",
        "Athens",
        "Madrid",
        "Dusseldorf",
        "Stockholm",
        "Dublin",
        "Manchester",
        "Berlin"
      ],
      "countries": [
        "FI",
        "SE",
        "NO",
        "TR",
        "GB",
        "NL",
        "AT",
        "DE",
        "IE",
        "PL",
        "PT",
        "FR",
        "ES",
        "CH",
        "GR",
        "DK",
        "IT",
        "BE"
      ],
      "thumbnail": [
        "https://raw.githubusercontent.com/eurodatacube/eodash-assets/main/collections/E13d_flying_planes/E13d_flying_planes_photo.jpg"
      ],
      "tags": [
        "Copernicus",
        "Mobility",
        "Air traffic",
        "Open data",
        "Community"
      ],
      "agency": [
        "ESA"
      ]
    },
    {
      "rel": "child",
      "href": "./cargo_boats_port/collection.json",
      "type": "application/json",
      "title": "Cargo boats in ports",
      "subtitle": "Changes in the number of boats in ports",
      "code": "E13e",
      "id": "cargo_boats_port",
      "themes": [
        "economy"
      ],
      "subcode": "E13e",
      "cities": [
        "Gioia Tauro",
        "Genoa"
      ],
      "countries": [
        "IT"
      ],
      "thumbnail": [
        "https://raw.githubusercontent.com/eurodatacube/eodash-assets/main/collections/E13e_cargo_boats_port/E13e_cargo_boats_port_photo.jpg"
      ],
      "tags": [
        "Ports",
        "Maritime",
        "Traffic"
      ],
      "agency": [
        "ESA"
      ],
      "insituSources": [
        "AIS"
      ]
    },
    {
      "rel": "child",
      "href": "./fishing_boats_port/collection.json",
      "type": "application/json",
      "title": "Fishing boats in ports",
      "subtitle": "Changes in the number of boats in ports",
      "code": "E13f",
      "id": "fishing_boats_port",
      "themes": [
        "economy"
      ],
      "subcode": "E13f",
      "cities": [
        "Gioia Tauro",
        "Genoa"
      ],
      "countries": [
        "IT"
      ],
      "thumbnail": [
        "https://raw.githubusercontent.com/eurodatacube/eodash-assets/main/collections/E13f_fishing_boats_port/E13f_fishing_boats_port.jpg"
      ],
      "tags": [
        "Ports",
        "Maritime",
        "Traffic"
      ],
      "agency": [
        "ESA"
      ],
      "insituSources": [
        "AIS"
      ]
    },
    {
      "rel": "child",
      "href": "./trucks_port/collection.json",
      "type": "application/json",
      "title": "Commercial fluxes",
      "subtitle": "Changes in the number of trucks in ports",
      "code": "E13n",
      "id": "trucks_port",
      "themes": [
        "economy"
      ],
      "subcode": "E13n",
      "cities": [
        "Gijon"
      ],
      "countries": [
        "ES"
      ],
      "thumbnail": [
        "https://raw.githubusercontent.com/eurodatacube/eodash-assets/main/collections/E13n_trucks_port/E13n_trucks_port_photo.jpg"
      ],
      "tags": [
        "Ports",
        "Traffic"
      ],
      "agency": [
        "ESA"
      ],
      "insituSources": [
        "Mobile"
      ]
    },
    {
      "rel": "child",
      "href": "./industrial_inventory/collection.json",
      "type": "application/json",
      "title": "Automobile inventory level",
      "subtitle": "Inventory level in logisitc areas of production sites",
      "code": "E8",
      "id": "industrial_inventory",
      "themes": [
        "economy"
      ],
      "subcode": "E8",
      "satellite": [
        "Sentinel-1",
        "ICEYE SAR"
      ],
      "sensor": [
        "C-SAR"
      ],
      "cities": [
        "Bremen",
        "Barcelona",
        "Mioveni",
        "Zwickau",
        "Russelsheim",
        "Saarlouis",
        "Craiova",
        "Regensburg",
        "Koln",
        "Emden",
        "Nosovice",
        "Kvasiny",
        "Cassino",
        "Sindelfingen",
        "Ghent",
        "Neckarsulm",
        "Ingolstadt",
        "Martorell",
        "Eisenach",
        "Swindon",
        "Leipzig",
        "Wolfsburg",
        "Dingolfing"
      ],
      "countries": [
        "RO",
        "CZ",
        "GB",
        "DE",
        "IT",
        "ES",
        "BE"
      ],
      "thumbnail": [
        "https://raw.githubusercontent.com/eurodatacube/eodash-assets/main/collections/E8_industrial_inventory/E8_industrial_inventory_photo.jpg"
      ],
      "tags": [
        "Copernicus",
        "Multi-sensors"
      ],
      "agency": [
        "European Commission",
        "ESA"
      ],
      "otherSources": [
        "Multi-sensors"
      ]
    },
    {
      "rel": "child",
      "href": "./ESDL_Hydrology_Precipitation/collection.json",
      "type": "application/json",
      "title": "Daily precipitation product",
      "code": "ESDL_Hydrology_Precipitation",
      "id": "ESDL_Hydrology_Precipitation",
      "themes": [
        "agriculture",
        "water"
      ],
      "subcode": "ESDL_Hydrology_Precipitation",
      "thumbnail": [
        "https://raw.githubusercontent.com/eurodatacube/eodash-assets/main/collections/ESDL_Hydrology_Precipitation/ESDL_Hydrology_Precipitation.jpg"
      ],
      "yAxis": "mm/day",
      "tags": [
        "Open data",
        "precipitation",
        "CPC",
        "GPM",
        "CHELSA Climatology"
      ],
      "agency": [
        "EURAC"
      ],
      "otherSources": [
        "GPM",
        "CPC",
        "model",
        "ERA5"
      ]
    },
    {
      "rel": "child",
      "href": "./GHS-BUILT-S-R2023A/collection.json",
      "type": "application/json",
      "title": "GHS-BUILT-S-R2023A",
      "subtitle": "GHS built-up surface dataset GHS-BUILT-S_GLOBE_R2023A",
      "code": "GHSBUILT",
      "id": "GHS-BUILT-S-R2023A",
      "themes": [
        "economy"
      ],
      "subcode": "GHSBUILT",
      "satellite": [
        "Sentinel-2"
      ],
      "sensor": [
        "MSI"
      ],
      "thumbnail": [
        "https://raw.githubusercontent.com/eurodatacube/eodash-assets/main/collections/GHS-BUILT-S-R2023A/GHS-BUILT-S-R2023A_photo.jpg"
      ],
      "tags": [
        "Copernicus",
        "Human settlement",
        "Human activities",
        "EMS",
        "Open data"
      ],
      "agency": [
        "European Commission"
      ]
    },
    {
      "rel": "child",
      "href": "./CO_3_daily/collection.json",
      "type": "application/json",
      "title": "Carbon Monoxide observed by Sentinel-5p TROPOMI",
      "subtitle": "Global 3-daily Carbon monoxide",
      "code": "N1_CO",
      "id": "CO_3_daily",
      "themes": [
        "air",
        "extremes"
      ],
      "subcode": "N1_CO",
      "satellite": [
        "Sentinel-5P"
      ],
      "sensor": [
        "TROPOMI"
      ],
      "thumbnail": [
        "https://raw.githubusercontent.com/eurodatacube/eodash-assets/main/collections/N1_CO/N1_CO_photo.jpg"
      ],
      "tags": [
        "Air quality",
        "CO",
        "Open data",
        "Air pollution"
      ],
      "agency": [
        "ESA"
      ]
    },
    {
      "rel": "child",
      "href": "./NO2_daily/collection.json",
      "type": "application/json",
      "title": "Air Quality (tropospheric NO2 concetrations)",
      "subtitle": "Daily Nitrogen Dioxide",
      "code": "N1_NO2",
      "id": "NO2_daily",
      "themes": [
        "air"
      ],
      "subcode": "N1_NO2",
      "satellite": [
        "Sentinel-5P"
      ],
      "sensor": [
        "TROPOMI"
      ],
      "thumbnail": [
        "https://raw.githubusercontent.com/eurodatacube/eodash-assets/main/collections/N1_NO2/N1_NO2_photo.jpg"
      ],
      "tags": [
        "Air quality",
        "NO2",
        "Open data",
        "Air pollution"
      ],
      "agency": [
        "ESA"
      ]
    },
    {
      "rel": "child",
      "href": "./OW_Covid_19_vaccinations/collection.json",
      "type": "application/json",
      "title": "Covid-19 Vaccinations",
      "code": "OW",
      "id": "OW_Covid_19_vaccinations",
      "themes": [
        "health"
      ],
      "subcode": "OW",
      "cities": [
        "/"
      ],
      "countries": [
        "Spain",
        "Italy",
        "Serbia",
        "Sweden",
        "Bulgaria",
        "Albania",
        "Austria",
        "Estonia",
        "Switzerland",
        "Germany",
        "Czechia",
        "Ireland",
        "Latvia",
        "Lithuania",
        "Finland",
        "Slovakia",
        "Luxembourg",
        "Bosnia and Herzegovina",
        "United Kingdom",
        "Hungary",
        "Norway",
        "Turkey",
        "Croatia",
        "France",
        "Kosovo",
        "Netherlands",
        "Portugal",
        "Malta",
        "Belgium",
        "North Macedonia",
        "Poland",
        "Romania",
        "Denmark",
        "Slovenia",
        "Greece"
      ],
      "thumbnail": [
        "https://raw.githubusercontent.com/eurodatacube/eodash-assets/main/collections/OW_Covid_19_vaccinations/OW_Covid_19_vaccinations_photo.jpg"
      ],
      "tags": [
        "Covid-19",
        "Human activities",
        "Open data"
      ],
      "agency": [
        "ESA"
      ],
      "insituSources": [
        "Other"
      ]
    },
    {
      "rel": "child",
      "href": "./OX_Crude_Oil_Storage_Index/collection.json",
      "type": "application/json",
      "title": "Crude Oil Storage Index",
      "subtitle": "Level of oil in tanks based on SAR and optical data",
      "code": "OX",
      "id": "OX_Crude_Oil_Storage_Index",
      "themes": [
        "economy"
      ],
      "subcode": "OX",
      "satellite": [
        "Sentinel-1",
        "Sentinel-2"
      ],
      "sensor": [
        "C-SAR",
        "MSI"
      ],
      "cities": [
        "Elefsina",
        "Le Havre",
        "Teesport",
        "Grangemouth",
        "Sarroch",
        "Tarragona",
        "Rotterdam",
        "Wilhelmshaven",
        "Schwechat",
        "Pachi",
        "Cartagena",
        "Finnart",
        "Sullom Voe",
        "Cork",
        "Antwerp",
        "Omisalj",
        "Thessaloniki",
        "Trieste",
        "Dalmeny",
        "Corinth",
        "Algeciras",
        "Aspropyrgos",
        "Fos-Lavera",
        "Godorf Wesseling"
      ],
      "countries": [
        "GB",
        "NL",
        "AT",
        "IE",
        "DE",
        "HR",
        "GR",
        "IT",
        "FR",
        "ES",
        "BE"
      ],
      "thumbnail": [
        "https://raw.githubusercontent.com/eurodatacube/eodash-assets/main/collections/OX_Crude_Oil_Storage_Index/OX_Crude_Oil_Storage_Index_photo.jpg"
      ],
      "tags": [
        "Copernicus",
        "Human activities",
        "Ports",
        "Maritime",
        "Multi-sensors"
      ],
      "agency": [
        "ESA"
      ],
      "insituSources": [
        "AIS",
        "Other"
      ]
    },
    {
      "rel": "child",
      "href": "./OX_EU_Crude_Oil_Storage_Index/collection.json",
      "type": "application/json",
      "title": "Crude Oil Storage Index Europe",
      "subtitle": "Level of oil in tanks based on SAR and optical data Europe",
      "code": "OX_EU",
      "id": "OX_EU_Crude_Oil_Storage_Index",
      "themes": [
        "economy"
      ],
      "subcode": "OX_EU",
      "satellite": [
        "Sentinel-1",
        "Sentinel-2"
      ],
      "sensor": [
        "C-SAR",
        "MSI"
      ],
      "cities": [
        "/"
      ],
      "countries": [
        "/"
      ],
      "thumbnail": [
        "https://raw.githubusercontent.com/eurodatacube/eodash-assets/main/collections/OX_Crude_Oil_Storage_Index/OX_EU_Crude_Oil_Storage_Index_photo.jpg"
      ],
      "tags": [
        "Copernicus",
        "Human activities",
        "Ports",
        "Maritime",
        "Multi-sensors"
      ],
      "agency": [
        "ESA"
      ],
      "insituSources": [
        "AIS",
        "Other"
      ]
    },
    {
      "rel": "child",
      "href": "./WASDI_FLOOD/collection.json",
      "type": "application/json",
      "title": "Flood mapping",
      "subtitle": "Automated flood map",
      "code": "WASDI_FLOOD",
      "id": "WASDI_FLOOD",
      "themes": [
        "extremes"
      ],
      "subcode": "WASDI_FLOOD",
      "satellite": [
        "Sentinel-1",
        "Sentinel-2"
      ],
      "sensor": [
        "SAR",
        "MSI"
      ],
      "thumbnail": [
        "https://raw.githubusercontent.com/eurodatacube/eodash-assets/main/collections/WASDI_FLOOD/WASDI_FLOOD.jpg"
      ],
      "tags": [
        "Copernicus Services",
        "Flood",
        "Open data",
        "Multi-sensors",
        "Copernicus",
        "Climate change service",
        "Urban area",
        "Disasters",
        "Sentinel"
      ],
      "agency": [
        "ESA"
      ]
    },
    {
      "rel": "self",
      "href": "https://eurodatacube.github.io/eodash-catalog/RACE/catalog.json",
      "type": "application/json"
    }
  ],
  "title": "RACE"
}