{
  "type": "Collection",
  "id": "ports_people_aq",
  "stac_version": "1.1.0",
  "description": "Port Activities, sources of pollution and NO2 levels",
  "links": [
    {
      "rel": "root",
      "href": "../../catalog.json",
      "type": "application/json",
      "title": "RACE"
    },
    {
      "rel": "item",
      "href": "./ports_people_aq/2020/Gioia Tauro.json",
      "type": "application/geo+json",
      "id": "IT16",
      "latlng": "38.45339,15.9024",
      "country": "IT",
      "city": "Gioia Tauro"
    },
    {
      "rel": "item",
      "href": "./ports_people_aq/2020/Genoa.json",
      "type": "application/geo+json",
      "id": "IT3",
      "latlng": "44.40572,8.93364",
      "country": "IT",
      "city": "Genoa"
    },
    {
      "rel": "parent",
      "href": "../collection.json",
      "type": "application/json",
      "title": "People sources"
    }
  ],
  "subtitle": "Port Activities, sources of pollution and NO2 levels",
  "yAxis": "Normalized NO2 concentration & Mean number of people",
  "themes": [
    "economy",
    "air"
  ],
  "tags": [
    "Air quality",
    "NO2",
    "Ports",
    "Multi-sensors"
  ],
  "agency": [
    "ESA"
  ],
  "subcode": "C2",
  "sensor": [
    "TROPOMI"
  ],
  "satellite": [
    "Sentinel-5P",
    "GNSS"
  ],
  "insituSources": [
    "AIS",
    "Mobile"
  ],
  "geoDBID": "C2",
  "endpointtype": "GeoDB",
  "title": "People sources",
  "extent": {
    "spatial": {
      "bbox": [
        [
          8.92364,
          38.44339,
          15.9124,
          44.41572
        ]
      ]
    },
    "temporal": {
      "interval": [
        [
          "2020-02-01T00:00:00Z",
          "2020-05-01T00:00:00Z"
        ]
      ]
    }
  },
  "license": "other",
  "providers": [
    {
      "name": "e-GEOS",
      "url": "https://www.e-geos.it/#/"
    },
    {
      "name": "ExpertLab",
      "url": "http://www.expertlab.it/"
    },
    {
      "name": "CherryData",
      "url": "https://www.cherry-data.com/"
    }
  ],
  "summaries": {
    "cities": [
      "Gioia Tauro",
      "Genoa"
    ],
    "countries": [
      "IT"
    ]
  },
  "assets": {
    "reference_1": {
      "href": "https://www.imo.org/en/OurWork/Safety/Pages/AIS.aspx",
      "type": "text/html",
      "title": "AIS data",
      "roles": [
        "metadata"
      ]
    },
    "reference_2": {
      "href": "https://www.tomtom.com/products/traffic-and-travel-information/",
      "type": "text/html",
      "title": "TomTom data",
      "roles": [
        "metadata"
      ]
    },
    "reference_3": {
      "href": "https://covidtracker.bsg.ox.ac.uk/",
      "type": "text/html",
      "title": "Oxford University’s coronavirus government response tracker",
      "roles": [
        "metadata"
      ]
    }
  }
}